LICENSE
MANIFEST.in
README.rst
setup.cfg
setup.py
commenting/__init__.py
commenting/admin.py
commenting/apps.py
commenting/forms.py
commenting/models.py
commenting/tests.py
commenting/urls.py
commenting/views.py
commenting/templates/comment-form.html
commenting/templates/comment.html
commenting/templatetags/__init__.py
commenting/templatetags/comment_form_tag.py
commenting/templatetags/custom_tags.py
django_commenting.egg-info/PKG-INFO
django_commenting.egg-info/SOURCES.txt
django_commenting.egg-info/dependency_links.txt
django_commenting.egg-info/top_level.txt