Metadata-Version: 2.1
Name: django-commenting
Version: 0.3
Summary: A Django app to add nested commenting feature to the user django application.
Home-page: https://www.example.com/
Author: Marvin
Author-email: aviavi@gmail.com
License: MIT
Keywords: Django,commenting,nested comments
Classifier: Environment :: Web Environment
Classifier: Framework :: Django
Classifier: Intended Audience :: Developers
Classifier: License :: OSI Approved :: MIT License
Classifier: Operating System :: OS Independent
Classifier: Programming Language :: Python
Classifier: Programming Language :: Python :: 3
Classifier: Programming Language :: Python :: 3 :: Only
Classifier: Programming Language :: Python :: 3.8
Classifier: Programming Language :: Python :: 3.9
Classifier: Topic :: Software Development :: Libraries :: Python Modules
Classifier: Topic :: Internet :: WWW/HTTP :: Dynamic Content
License-File: LICENSE
